odoo/addons/product_pricelist_revision/README.rst
odoo/addons/product_pricelist_revision/__init__.py
odoo/addons/product_pricelist_revision/__manifest__.py
odoo/addons/product_pricelist_revision/i18n/ca.po
odoo/addons/product_pricelist_revision/i18n/es.po
odoo/addons/product_pricelist_revision/i18n/product_pricelist_revision.pot
odoo/addons/product_pricelist_revision/models/__init__.py
odoo/addons/product_pricelist_revision/models/pricelist.py
odoo/addons/product_pricelist_revision/readme/CONFIGURE.rst
odoo/addons/product_pricelist_revision/readme/CONTRIBUTORS.rst
odoo/addons/product_pricelist_revision/readme/DESCRIPTION.rst
odoo/addons/product_pricelist_revision/readme/USAGE.rst
odoo/addons/product_pricelist_revision/security/ir.model.access.csv
odoo/addons/product_pricelist_revision/static/description/icon.png
odoo/addons/product_pricelist_revision/static/description/index.html
odoo/addons/product_pricelist_revision/tests/__init__.py
odoo/addons/product_pricelist_revision/tests/test_product_pricelist_revision.py
odoo/addons/product_pricelist_revision/views/pricelist_view.xml
odoo/addons/product_pricelist_revision/wizards/__init__.py
odoo/addons/product_pricelist_revision/wizards/pricelist_duplicate_wizard.py
odoo/addons/product_pricelist_revision/wizards/pricelist_duplicate_wizard_view.xml
odoo14_addon_product_pricelist_revision-14.0.1.0.2.dist-info/METADATA
odoo14_addon_product_pricelist_revision-14.0.1.0.2.dist-info/WHEEL
odoo14_addon_product_pricelist_revision-14.0.1.0.2.dist-info/top_level.txt
odoo14_addon_product_pricelist_revision-14.0.1.0.2.dist-info/RECORD
